SendKeys.py
_sendkeys.pyd
SendKeys-0.3.data/data/README.txt
SendKeys-0.3.data/data/doc/SendKeys.txt
SendKeys-0.3.dist-info/DESCRIPTION.rst
SendKeys-0.3.dist-info/METADATA
SendKeys-0.3.dist-info/metadata.json
SendKeys-0.3.dist-info/RECORD
SendKeys-0.3.dist-info/top_level.txt
SendKeys-0.3.dist-info/WHEEL
